nipanbo_mcp_educate_time/__init__.py
nipanbo_mcp_educate_time/server.py
nipanbo_mcp_time/__init__.py
nipanbo_mcp_time/fastmcp.py
nipanbo_mcp_time1-0.2.0.dist-info/METADATA
nipanbo_mcp_time1-0.2.0.dist-info/WHEEL
nipanbo_mcp_time1-0.2.0.dist-info/entry_points.txt
nipanbo_mcp_time1-0.2.0.dist-info/top_level.txt
nipanbo_mcp_time1-0.2.0.dist-info/RECORD
