Metadata-Version: 2.4
Name: nipanbo-mcp-time1
Version: 0.2.0
Requires-Dist: mcp
Dynamic: requires-dist
